{
  "minecraft:recipes/transportation/acacia_boat": {
    "criteria": {
      "in_water": "2022-10-31 05:07:43 +0000"
    },
    "done": true
  },
  "minecraft:recipes/building_blocks/sponge": {
    "criteria": {
      "has_wet_sponge": "2023-04-15 06:02:24 +0000"
    },
    "done": true
  },
  "minecraft:recipes/transportation/oak_boat": {
    "criteria": {
      "in_water": "2022-10-31 05:07:43 +0000"
    },
    "done": true
  },
  "splatcraft:recipes/splatcraft_general/remote_pedestal": {
    "criteria": {
      "has_remote": "2022-10-31 04:42:27 +0000"
    },
    "done": true
  },
  "minecraft:recipes/transportation/dark_oak_boat": {
    "criteria": {
      "in_water": "2022-10-31 05:07:43 +0000"
    },
    "done": true
  },
  "minecraft:adventure/root": {
    "criteria": {
      "killed_by_something": "2022-10-31 04:43:15 +0000"
    },
    "done": true
  },
  "minecraft:recipes/decorations/chest": {
    "criteria": {
      "has_lots_of_items": "2022-10-31 05:06:36 +0000"
    },
    "done": true
  },
  "minecraft:recipes/transportation/birch_boat": {
    "criteria": {
      "in_water": "2022-10-31 05:07:43 +0000"
    },
    "done": true
  },
  "minecraft:recipes/transportation/jungle_boat": {
    "criteria": {
      "in_water": "2022-10-31 05:07:43 +0000"
    },
    "done": true
  },
  "minecraft:recipes/transportation/spruce_boat": {
    "criteria": {
      "in_water": "2022-10-31 05:07:43 +0000"
    },
    "done": true
  },
  "minecraft:recipes/brewing/cauldron": {
    "criteria": {
      "has_water_bucket": "2023-04-15 06:12:14 +0000"
    },
    "done": true
  },
  "minecraft:adventure/adventuring_time": {
    "criteria": {
      "minecraft:plains": "2022-10-31 04:38:53 +0000"
    },
    "done": false
  },
  "DataVersion": 2586
}